setup.json
setup.py
src/dt_authentication/__init__.py
src/dt_authentication/cli.py
src/dt_authentication/exceptions.py
src/dt_authentication/scope.py
src/dt_authentication/token.py
src/dt_authentication/utils.py
src/dt_authentication.egg-info/PKG-INFO
src/dt_authentication.egg-info/SOURCES.txt
src/dt_authentication.egg-info/dependency_links.txt
src/dt_authentication.egg-info/entry_points.txt
src/dt_authentication.egg-info/requires.txt
src/dt_authentication.egg-info/top_level.txt