Metadata-Version: 2.1
Name: dt-authentication
Version: 2.2.0
Home-page: http://github.com/duckietown/lib-dt-authentication
Author: Andrea F. Daniele
Author-email: afdaniele@duckietown.com
Requires-Dist: base58
Requires-Dist: ecdsa
Requires-Dist: requests
